{
	"design__io": 105,
	"design__die__area": 95919.4,
	"design__core__area": 85280.5,
	"design__instance__count": 5495,
	"design__instance__area": 43569.3,
	"design__instance__count__stdcell": 5495,
	"design__instance__area__stdcell": 43569.3,
	"design__instance__count__macros": 0,
	"design__instance__area__macros": 0,
	"design__instance__count__padcells": 0,
	"design__instance__area__padcells": 0,
	"design__instance__count__cover": 0,
	"design__instance__area__cover": 0,
	"design__instance__utilization": 0.510894,
	"design__instance__utilization__stdcell": 0.510894,
	"design__rows": 107,
	"design__rows:unithd": 107,
	"design__sites": 68159,
	"design__sites:unithd": 68159,
	"design__instance__count__class:fill_cell": 12306,
	"design__instance__area__class:fill_cell": 41711.3,
	"design__instance__count__class:tap_cell": 1199,
	"design__instance__area__class:tap_cell": 1500.19,
	"design__instance__count__class:antenna_cell": 8,
	"design__instance__area__class:antenna_cell": 20.0192,
	"design__instance__count__class:timing_repair_buffer": 770,
	"design__instance__area__class:timing_repair_buffer": 6477.46,
	"design__instance__count__class:inverter": 73,
	"design__instance__area__class:inverter": 274.013,
	"design__instance__count__class:multi_input_combinational_cell": 3445,
	"design__instance__area__class:multi_input_combinational_cell": 35297.6,
	"design__instance__count": 17801,
	"design__instance__area": 85280.5,
	"flow__warnings__count": 4,
	"flow__errors__count": 0,
	"flow__warnings__count:STA-0366": 2,
	"flow__warnings__count:STA-0419": 1,
	"flow__warnings__count:STA-0450": 1,
	"flow__warnings__type_count": 3
}